{"cameraMode":{"drawMode":0,"name":"Shaded","section":"Shading Mode"},"sceneLighting":false,"audioPlay":false,"sceneViewState":{"showFog":true,"showMaterialUpdate":false,"showSkybox":false,"showFlares":true,"showImageEffects":true,"showParticleSystems":true,"showVisualEffectGraphs":true,"m_FxEnabled":true},"in2DMode":false,"pivot":{"x":-144.63616943359376,"y":119.13152313232422,"z":856.6032104492188},"rotation":{"x":0.09573284536600113,"y":0.808647096157074,"z":-0.13460898399353028,"w":0.5649080872535706},"size":10.304076194763184,"orthographic":false}